{
  "rs": 1,
  "errorCode": "",
  "errorMessage": "",
  "resultMessage": {
    "total": 20,
    "totalSubQuestionNum": 20,
    "questionList": [
      {
        "questionContent": "柯蒂斯出版公司率先成立了市场调查部门，并编写了（）一书，这是第一本有关市场研究的专著。",
        "questionId": 1460893,
        "answerTime": 0,
        "correct": 2,
        "studentScore": 0,
        "optionList": [
          {
            "optionContent": "《销售圣经》",
            "optionTitle": "A",
            "sequence": 0,
            "correct": 0
          },
          {
            "optionContent": "《市场调研与分析》",
            "optionTitle": "B",
            "sequence": 1,
            "correct": 0
          },
          {
            "optionContent": "《市场调研技术》",
            "optionTitle": "C",
            "sequence": 2,
            "correct": 0
          },
          {
            "optionContent": "《销售机会》",
            "optionTitle": "D",
            "sequence": 3,
            "correct": 1
          }
        ],
        "studentAnswer": "",
        "canAnswer": 1,
        "analysis": "1911年，美国当时最大的柯蒂斯出版公司率先成立了市场调查部门，并编写了<b>《销售机会》</b>一书，这是第一本有关市场研究的专著。",
        "avgAnswerTime": 6,
        "avgCorrectRate": "92.0%",
        "score": 1.0,
        "sequence": 1,
        "avgScore": 0.0,
        "errorProneAnswer": "B",
        "questionAnswer": "D",
        "questionSource": "模拟题",
        "mainNodeName": "一、市场调查的起源",
        "analysisType": -1,
        "favorite": 0,
        "questionType": "SINGLE_CHOICE"
      },
      {
        "questionContent": "（）是市场调查产生和发展的基础和原动力。",
        "questionId": 1503219,
        "answerTime": 0,
        "correct": 2,
        "studentScore": 0,
        "optionList": [
          {
            "optionContent": "商品的交换",
            "optionTitle": "A",
            "sequence": 0,
            "correct": 0
          },
          {
            "optionContent": "商品的生产",
            "optionTitle": "B",
            "sequence": 1,
            "correct": 0
          },
          {
            "optionContent": "经济的发展",
            "optionTitle": "C",
            "sequence": 2,
            "correct": 1
          },
          {
            "optionContent": "文化的发展",
            "optionTitle": "D",
            "sequence": 3,
            "correct": 0
          }
        ],
        "studentAnswer": "",
        "canAnswer": 1,
        "analysis": "<b>市场调查</b>是随着近代商品生产和商品交换的发展而出现的，经济的发展是市场调查产生和发展的基础和原动力。",
        "avgAnswerTime": 10,
        "avgCorrectRate": "93.0%",
        "score": 1.0,
        "sequence": 2,
        "avgScore": 0.0,
        "errorProneAnswer": "A",
        "questionAnswer": "C",
        "questionSource": "模拟题",
        "mainNodeName": "一、市场调查的起源",
        "analysisType": -1,
        "favorite": 0,
        "questionType": "SINGLE_CHOICE"
      },
      {
        "questionContent": "市场调查者在（）开始使用商业普查的方式，并进行统计分析。",
        "questionId": 1460995,
        "answerTime": 0,
        "correct": 2,
        "studentScore": 0,
        "optionList": [
          {
            "optionContent": "问卷调查时期",
            "optionTitle": "A",
            "sequence": 0,
            "correct": 0
          },
          {
            "optionContent": "组织接受的时期",
            "optionTitle": "B",
            "sequence": 1,
            "correct": 0
          },
          {
            "optionContent": "计量调查时期",
            "optionTitle": "C",
            "sequence": 2,
            "correct": 1
          },
          {
            "optionContent": "技术进步时期",
            "optionTitle": "D",
            "sequence": 3,
            "correct": 0
          }
        ],
        "studentAnswer": "",
        "canAnswer": 1,
        "analysis": "从1940年到1960年，我们把这一时期称之为<b>计量调查时期</b>。市场调查者<b>在这一时期</b>开始使用商业普查的方式，并进行统计分析。",
        "avgAnswerTime": 10,
        "avgCorrectRate": "86.0%",
        "score": 1.0,
        "sequence": 3,
        "avgScore": 0.0,
        "errorProneAnswer": "A",
        "questionAnswer": "C",
        "questionSource": "模拟题",
        "mainNodeName": "市场调查在世界范围内的发展",
        "analysisType": -1,
        "favorite": 0,
        "questionType": "SINGLE_CHOICE"
      },
      {
        "questionContent": "工业革命之前的市场调查阶段，我们称之为（）。",
        "questionId": 1592458,
        "answerTime": 0,
        "correct": 2,
        "studentScore": 0,
        "optionList": [
          {
            "optionContent": "早期发展时期",
            "optionTitle": "A",
            "sequence": 0,
            "correct": 0
          },
          {
            "optionContent": "问卷调查时期",
            "optionTitle": "B",
            "sequence": 1,
            "correct": 0
          },
          {
            "optionContent": "前市场调查时期",
            "optionTitle": "C",
            "sequence": 2,
            "correct": 1
          },
          {
            "optionContent": "计量调查时期",
            "optionTitle": "D",
            "sequence": 3,
            "correct": 0
          }
        ],
        "studentAnswer": "",
        "canAnswer": 1,
        "analysis": "市场调查在世界范围内的发展历程大致可分为以下几个阶段：<img src=\"https://sfs-public.shangdejigou.cn/teach-resource/question_content/picture/175a0758c84f9406b45267e3a643f165/image.png\" alt=\"\" width=\"277\" height=\"201\"><br>故本题正确答案为：C",
        "avgAnswerTime": 6,
        "avgCorrectRate": "91.0%",
        "score": 1.0,
        "sequence": 4,
        "avgScore": 0.0,
        "questionAnswer": "C",
        "questionSource": "模拟题",
        "mainNodeName": "市场调查在世界范围内的发展",
        "analysisType": -1,
        "favorite": 0,
        "questionType": "SINGLE_CHOICE"
      },
      {
        "questionContent": "（）是市场营销战略组合中最活跃的因素。",
        "questionId": 2292724,
        "answerTime": 0,
        "correct": 2,
        "studentScore": 0,
        "optionList": [
          {
            "optionContent": "产品",
            "optionTitle": "A",
            "sequence": 0,
            "correct": 0
          },
          {
            "optionContent": "价格",
            "optionTitle": "B",
            "sequence": 1,
            "correct": 1
          },
          {
            "optionContent": "渠道",
            "optionTitle": "C",
            "sequence": 2,
            "correct": 0
          },
          {
            "optionContent": "​宣传<br>",
            "optionTitle": "D",
            "sequence": 3,
            "correct": 0
          }
        ],
        "studentAnswer": "",
        "canAnswer": 1,
        "analysis": "<b>价格</b>是市场营销战略组合中最活跃的因素",
        "avgAnswerTime": 9,
        "avgCorrectRate": "86.0%",
        "score": 1.0,
        "sequence": 5,
        "avgScore": 0.0,
        "errorProneAnswer": "D",
        "questionAnswer": "B",
        "questionSource": "模拟题",
        "mainNodeName": "市场调查有助于企业实行正确的价格策略",
        "analysisType": -1,
        "favorite": 0,
        "questionType": "SINGLE_CHOICE"
      },
      {
        "questionContent": "客观上已经存在或即将形成，而尚未被人们认识的市场是指（）",
        "questionId": 1497288,
        "answerTime": 0,
        "correct": 2,
        "studentScore": 0,
        "optionList": [
          {
            "optionContent": "电子市场",
            "optionTitle": "A",
            "sequence": 0,
            "correct": 0
          },
          {
            "optionContent": "成熟市场",
            "optionTitle": "B",
            "sequence": 1,
            "correct": 0
          },
          {
            "optionContent": "细分市场",
            "optionTitle": "C",
            "sequence": 2,
            "correct": 0
          },
          {
            "optionContent": "市场机会",
            "optionTitle": "D",
            "sequence": 3,
            "correct": 1
          }
        ],
        "studentAnswer": "",
        "canAnswer": 1,
        "analysis": "<b>市场机会</b>就是市场上存在的未满足的需求。有时人们称它为潜在的市场，亦即客观上已经存在或即将形成，而尚未被人们认识的市场。",
        "avgAnswerTime": 7,
        "avgCorrectRate": "96.0%",
        "score": 1.0,
        "sequence": 6,
        "avgScore": 0.0,
        "questionAnswer": "D",
        "questionSource": "模拟题",
        "mainNodeName": "市场调查有助于企业发现新的市场机会",
        "analysisType": -1,
        "favorite": 0,
        "questionType": "SINGLE_CHOICE"
      },
      {
        "questionContent": "在市场调查的原则中，（）是指收集、发送、接收、加工、传递和利用市场调查资料的时间间隔要短，效率要高。",
        "questionId": 1461256,
        "answerTime": 0,
        "correct": 2,
        "studentScore": 0,
        "optionList": [
          {
            "optionContent": "科学性原则",
            "optionTitle": "A",
            "sequence": 0,
            "correct": 0
          },
          {
            "optionContent": "时效性原则",
            "optionTitle": "B",
            "sequence": 1,
            "correct": 1
          },
          {
            "optionContent": "系统性原则",
            "optionTitle": "C",
            "sequence": 2,
            "correct": 0
          },
          {
            "optionContent": "准确性原则",
            "optionTitle": "D",
            "sequence": 3,
            "correct": 0
          }
        ],
        "studentAnswer": "",
        "canAnswer": 1,
        "analysis": "<b>时效性原则</b>是指收集、发送、接收、加工、传递和利用市场调查资料的时间间隔要短，效率要高。",
        "avgAnswerTime": 9,
        "avgCorrectRate": "97.0%",
        "score": 1.0,
        "sequence": 7,
        "avgScore": 0.0,
        "questionAnswer": "B",
        "questionSource": "模拟题",
        "mainNodeName": "时效性原则",
        "analysisType": -1,
        "favorite": 0,
        "questionType": "SINGLE_CHOICE"
      },
      {
        "questionContent": "在市场调查的原则中，（）要求必须真实地、准确地描述客观现象的数量表现和属性特征，调查误差应尽可能小，没有系统性偏差，没有人为因素的干扰。",
        "questionId": 1461264,
        "answerTime": 0,
        "correct": 2,
        "studentScore": 0,
        "optionList": [
          {
            "optionContent": "经济性原则",
            "optionTitle": "A",
            "sequence": 0,
            "correct": 0
          },
          {
            "optionContent": "​系统性原则<br>",
            "optionTitle": "B",
            "sequence": 1,
            "correct": 0
          },
          {
            "optionContent": "科学性原则",
            "optionTitle": "C",
            "sequence": 2,
            "correct": 0
          },
          {
            "optionContent": "准确性原则",
            "optionTitle": "D",
            "sequence": 3,
            "correct": 1
          }
        ],
        "studentAnswer": "",
        "canAnswer": 1,
        "analysis": "<b>准确性原则</b>要求必须真实地、准确地描述客观现象的数量表现和属性特征，调查误差应尽可能小，没有系统性偏差，没有人为因素的干扰。",
        "avgAnswerTime": 12,
        "avgCorrectRate": "95.0%",
        "score": 1.0,
        "sequence": 8,
        "avgScore": 0.0,
        "errorProneAnswer": "B",
        "questionAnswer": "D",
        "questionSource": "模拟题",
        "mainNodeName": "准确性原则",
        "analysisType": -1,
        "favorite": 0,
        "questionType": "SINGLE_CHOICE"
      },
      {
        "questionContent": "市场调查不是一种简单的收集情报、信息的活动，为了在时间和经费有限的情况下，获得更多更准确的市场信息资料，就必须对调查的过程进行科学的安排。这指的是市场调查的（ ）原则。",
        "questionId": 1906773,
        "answerTime": 0,
        "correct": 2,
        "studentScore": 0,
        "optionList": [
          {
            "optionContent": "时效性",
            "optionTitle": "A",
            "sequence": 0,
            "correct": 0
          },
          {
            "optionContent": "经济性",
            "optionTitle": "B",
            "sequence": 1,
            "correct": 0
          },
          {
            "optionContent": "科学性",
            "optionTitle": "C",
            "sequence": 2,
            "correct": 1
          },
          {
            "optionContent": "系统性",
            "optionTitle": "D",
            "sequence": 3,
            "correct": 0
          }
        ],
        "studentAnswer": "",
        "canAnswer": 1,
        "analysis": "<img src=\"https://sfs-public.shangdejigou.cn/teach-resource/question_content/picture/7300c1a1baa9042329f9991d78816333/image.png\" alt=\"\" width=\"569\" height=\"223\"><br>",
        "avgAnswerTime": 13,
        "avgCorrectRate": "84.0%",
        "score": 1.0,
        "sequence": 9,
        "avgScore": 0.0,
        "questionAnswer": "C",
        "questionSource": "模拟题",
        "mainNodeName": "科学性原则",
        "analysisType": -1,
        "favorite": 0,
        "questionType": "SINGLE_CHOICE"
      },
      {
        "questionContent": "消费方面的调查属于（ ）",
        "questionId": 2137153,
        "answerTime": 0,
        "correct": 2,
        "studentScore": 0,
        "optionList": [
          {
            "optionContent": "政治环境调查",
            "optionTitle": "A",
            "sequence": 0,
            "correct": 0
          },
          {
            "optionContent": "​法律环境调查<br>",
            "optionTitle": "B",
            "sequence": 1,
            "correct": 0
          },
          {
            "optionContent": "自然环境调查",
            "optionTitle": "C",
            "sequence": 2,
            "correct": 0
          },
          {
            "optionContent": "经济环境调查",
            "optionTitle": "D",
            "sequence": 3,
            "correct": 1
          }
        ],
        "studentAnswer": "",
        "canAnswer": 1,
        "analysis": "政治环境调查应调查：①目标国家的政治制度和政策；②国家或地区之间的政治关系；③政治和社会动乱情况；④国有化政策。法律环境调查：市场调查人员必须了解有关法律、法规及政策。自然环境调查：主要包括生态环境、资源环境、能源环境等方面的调查。经济环境调查：生产方面的调查、<b>消费方面的调查</b>。故本题应选D项。",
        "avgAnswerTime": 17,
        "avgCorrectRate": "97.0%",
        "score": 1.0,
        "sequence": 10,
        "avgScore": 0.0,
        "errorProneAnswer": "C",
        "questionAnswer": "D",
        "questionSource": "江苏省-1904真题-第1题",
        "mainNodeName": "市场环境调查",
        "analysisType": -1,
        "favorite": 0,
        "questionType": "SINGLE_CHOICE"
      },
      {
        "questionContent": "在一定时期内，全社会在市场上用于购买商品和服务的货币支付能力是指（）",
        "questionId": 1645076,
        "answerTime": 0,
        "correct": 2,
        "studentScore": 0,
        "optionList": [
          {
            "optionContent": "社会购买力",
            "optionTitle": "A",
            "sequence": 0,
            "correct": 1
          },
          {
            "optionContent": "商品供应能力",
            "optionTitle": "B",
            "sequence": 1,
            "correct": 0
          },
          {
            "optionContent": "欲望",
            "optionTitle": "C",
            "sequence": 2,
            "correct": 0
          },
          {
            "optionContent": "社会需求",
            "optionTitle": "D",
            "sequence": 3,
            "correct": 0
          }
        ],
        "studentAnswer": "",
        "canAnswer": 1,
        "analysis": "<b>​</b>​破题点：全社会、购买<br>即社会购买力是指在一定时期内，全社会在市场上用于购买商品和服务的货币支付能力。本题易混项为B，商品供应能力是指现有商品生产或商品流转的规模、速度、结构状况以及能否满足消费需求。CD选项为无关干扰项。故本题正确答案为：A<br>",
        "avgAnswerTime": 12,
        "avgCorrectRate": "91.0%",
        "score": 1.0,
        "sequence": 11,
        "avgScore": 0.0,
        "questionAnswer": "A",
        "questionSource": "模拟题",
        "mainNodeName": "市场需求调查",
        "analysisType": -1,
        "favorite": 0,
        "questionType": "SINGLE_CHOICE"
      },
      {
        "questionContent": "预测性市场调查所回答的问题是（）",
        "questionId": 1465275,
        "answerTime": 0,
        "correct": 2,
        "studentScore": 0,
        "optionList": [
          {
            "optionContent": "是什么",
            "optionTitle": "A",
            "sequence": 0,
            "correct": 0
          },
          {
            "optionContent": "为什么",
            "optionTitle": "B",
            "sequence": 1,
            "correct": 0
          },
          {
            "optionContent": "未来市场前景如何",
            "optionTitle": "C",
            "sequence": 2,
            "correct": 1
          },
          {
            "optionContent": "如何做",
            "optionTitle": "D",
            "sequence": 3,
            "correct": 0
          }
        ],
        "studentAnswer": "",
        "canAnswer": 1,
        "analysis": "预测性市场调查是指为了预测市场供求变化趋势或企业生产经营前景而进行的具有推断性的调查。它所回答的问题是<b>“未来市场前景如何”</b>，其目的在于掌握未来市场的发展趋势，为经营管理决策和市场营销决策提供依据。",
        "avgAnswerTime": 8,
        "avgCorrectRate": "93.0%",
        "score": 1.0,
        "sequence": 12,
        "avgScore": 0.0,
        "errorProneAnswer": "D",
        "questionAnswer": "C",
        "questionSource": "模拟题",
        "mainNodeName": "按调查的目的和功能分类",
        "analysisType": -1,
        "favorite": 0,
        "questionType": "SINGLE_CHOICE"
      },
      {
        "questionContent": "工业普查、经济普查属于（）",
        "questionId": 1607079,
        "answerTime": 0,
        "correct": 2,
        "studentScore": 0,
        "optionList": [
          {
            "optionContent": "宏观方面的普查",
            "optionTitle": "A",
            "sequence": 0,
            "correct": 1
          },
          {
            "optionContent": "微观方面的普查",
            "optionTitle": "B",
            "sequence": 1,
            "correct": 0
          },
          {
            "optionContent": "中观方面的普查",
            "optionTitle": "C",
            "sequence": 2,
            "correct": 0
          },
          {
            "optionContent": "主观方面的普查",
            "optionTitle": "D",
            "sequence": 3,
            "correct": 0
          }
        ],
        "studentAnswer": "",
        "canAnswer": 1,
        "analysis": "<img src=\"https://sfs-public.shangdejigou.cn/teach-resource/question_content/picture/c2f898ed27bcd8e04fa6157756b7d6d3/image.png\" alt=\"\" width=\"413\" height=\"187\"><br>故本题正确答案为：A",
        "avgAnswerTime": 6,
        "avgCorrectRate": "97.0%",
        "score": 1.0,
        "sequence": 13,
        "avgScore": 0.0,
        "questionAnswer": "A",
        "questionSource": "模拟题",
        "mainNodeName": "市场普查的概念",
        "analysisType": -1,
        "favorite": 0,
        "questionType": "SINGLE_CHOICE"
      },
      {
        "questionContent": "如果按照普查资料的汇总方式来划分，我们还可以将普查分为一般普查和（）",
        "questionId": 1620209,
        "answerTime": 0,
        "correct": 2,
        "studentScore": 0,
        "optionList": [
          {
            "optionContent": "特殊普查",
            "optionTitle": "A",
            "sequence": 0,
            "correct": 0
          },
          {
            "optionContent": "​综合普查<br>",
            "optionTitle": "B",
            "sequence": 1,
            "correct": 0
          },
          {
            "optionContent": "快速普查",
            "optionTitle": "C",
            "sequence": 2,
            "correct": 1
          },
          {
            "optionContent": "专题普查",
            "optionTitle": "D",
            "sequence": 3,
            "correct": 0
          }
        ],
        "studentAnswer": "",
        "canAnswer": 1,
        "analysis": "<img src=\"https://sfs-public.shangdejigou.cn/teach-resource/question_content/picture/cae588b57d70681f8ec8850dab576515/image.png\" alt=\"\" width=\"251\" height=\"102\"><br>ABD选项为无关干扰项。故本题正确答案为：C",
        "avgAnswerTime": 9,
        "avgCorrectRate": "86.0%",
        "score": 1.0,
        "sequence": 14,
        "avgScore": 0.0,
        "questionAnswer": "C",
        "questionSource": "模拟题",
        "mainNodeName": "市场普查的方式",
        "analysisType": -1,
        "favorite": 0,
        "questionType": "SINGLE_CHOICE"
      },
      {
        "questionContent": "典型调查主要有三种方式，其中，按一定的标准将调查总体划分为若干类别，再从各类别中选取部分具有代表性的样本进行调查，这就是（）",
        "questionId": 1704543,
        "answerTime": 0,
        "correct": 2,
        "studentScore": 0,
        "optionList": [
          {
            "optionContent": "“解剖麻雀式”调查",
            "optionTitle": "A",
            "sequence": 0,
            "correct": 0
          },
          {
            "optionContent": "“划类选典式”调查",
            "optionTitle": "B",
            "sequence": 1,
            "correct": 1
          },
          {
            "optionContent": "“综合应用式”调查",
            "optionTitle": "C",
            "sequence": 2,
            "correct": 0
          },
          {
            "optionContent": "“归纳总结式”调查",
            "optionTitle": "D",
            "sequence": 3,
            "correct": 0
          }
        ],
        "studentAnswer": "",
        "canAnswer": 1,
        "analysis": "<img src=\"https://sfs-public.shangdejigou.cn/teach-resource/question_content/picture/6c26fa14f0e19354ed0125a64fed0ddb/image.png\" alt=\"\" width=\"479\" height=\"154\"><br>D选项为无关干扰项。故本题正确答案为：B",
        "avgAnswerTime": 14,
        "avgCorrectRate": "87.0%",
        "score": 1.0,
        "sequence": 15,
        "avgScore": 0.0,
        "questionAnswer": "B",
        "questionSource": "模拟题",
        "mainNodeName": "典型调查的方式",
        "analysisType": -1,
        "favorite": 0,
        "questionType": "SINGLE_CHOICE"
      },
      {
        "questionContent": "要根据调查任务的要求和调查对象的基本情况来确定选取的重点单位及数量。一般来说，要求重点单位应尽可能少，而其标志值在总体中所占的比重应尽可能大，以保证有足够的代表性。这体现了在选择重点单位时，应遵循（）",
        "questionId": 1630361,
        "answerTime": 0,
        "correct": 2,
        "studentScore": 0,
        "optionList": [
          {
            "optionContent": "目的性原则",
            "optionTitle": "A",
            "sequence": 0,
            "correct": 0
          },
          {
            "optionContent": "基础性原则",
            "optionTitle": "B",
            "sequence": 1,
            "correct": 0
          },
          {
            "optionContent": "时空性原则",
            "optionTitle": "C",
            "sequence": 2,
            "correct": 0
          },
          {
            "optionContent": "“少”“大”结合原则",
            "optionTitle": "D",
            "sequence": 3,
            "correct": 1
          }
        ],
        "studentAnswer": "",
        "canAnswer": 1,
        "analysis": "<b>​</b>​破题点：重点单位尽可能少，比重尽可能大。（“少”“大”结合）选择重点调查单位的原则如下：<img src=\"https://sfs-public.shangdejigou.cn/teach-resource/question_content/picture/cb6fb1ed40f209fac71bd0e48104fcd5/image.png\" alt=\"\" width=\"437\" height=\"223\"><br>助记：“少”“大”结合基础行（性），目的时空不可少。故本题正确答案为：D",
        "avgAnswerTime": 13,
        "avgCorrectRate": "92.0%",
        "score": 1.0,
        "sequence": 16,
        "avgScore": 0.0,
        "questionAnswer": "D",
        "questionSource": "模拟题",
        "mainNodeName": "选择重点调查单位的原则",
        "analysisType": -1,
        "favorite": 0,
        "questionType": "SINGLE_CHOICE"
      },
      {
        "questionContent": "所有研究方法中最生动、最有趣的一种调查方式是（）",
        "questionId": 1607936,
        "answerTime": 0,
        "correct": 2,
        "studentScore": 0,
        "optionList": [
          {
            "optionContent": "典型调查",
            "optionTitle": "A",
            "sequence": 0,
            "correct": 0
          },
          {
            "optionContent": "重点调查",
            "optionTitle": "B",
            "sequence": 1,
            "correct": 0
          },
          {
            "optionContent": "抽样调查",
            "optionTitle": "C",
            "sequence": 2,
            "correct": 0
          },
          {
            "optionContent": "个案调查",
            "optionTitle": "D",
            "sequence": 3,
            "correct": 1
          }
        ],
        "studentAnswer": "",
        "canAnswer": 1,
        "analysis": "<b>​</b>​本题属于理解记忆型题目。<br><img src=\"https://sfs-public.shangdejigou.cn/teach-resource/question_content/picture/c4d47b1068a9cb70a813843a77ba8b93/image.png\" alt=\"\" width=\"399\" height=\"39\"><br>助记：个案生动又有趣。故本题正确答案为：D",
        "avgAnswerTime": 10,
        "avgCorrectRate": "76.0%",
        "score": 1.0,
        "sequence": 17,
        "avgScore": 0.0,
        "errorProneAnswer": "A",
        "questionAnswer": "D",
        "questionSource": "模拟题",
        "mainNodeName": "个案调查的特点",
        "analysisType": -1,
        "favorite": 0,
        "questionType": "SINGLE_CHOICE"
      },
      {
        "questionContent": "（）是市场调查研究成果的集中体现，是对市场调查工作最集中的总结。",
        "questionId": 1465320,
        "answerTime": 0,
        "correct": 2,
        "studentScore": 0,
        "optionList": [
          {
            "optionContent": "调查方案",
            "optionTitle": "A",
            "sequence": 0,
            "correct": 0
          },
          {
            "optionContent": "调查报告",
            "optionTitle": "B",
            "sequence": 1,
            "correct": 1
          },
          {
            "optionContent": "​调查计划<br>",
            "optionTitle": "C",
            "sequence": 2,
            "correct": 0
          },
          {
            "optionContent": "​调查资料<br>",
            "optionTitle": "D",
            "sequence": 3,
            "correct": 0
          }
        ],
        "studentAnswer": "",
        "canAnswer": 1,
        "analysis": "<b>调查报告</b>是市场调查研究成果的集中体现，是对市场调查工作最集中的总结，而撰写调查报告是市场调查的重要环节，必须使调查报告在理论研究或实际工作中发挥重要作用，此外，还应对调查工作中的经验教训加以总结。",
        "avgAnswerTime": 8,
        "avgCorrectRate": "97.0%",
        "score": 1.0,
        "sequence": 18,
        "avgScore": 0.0,
        "questionAnswer": "B",
        "questionSource": "模拟题",
        "mainNodeName": "五、市场调查的总结阶段",
        "analysisType": -1,
        "favorite": 0,
        "questionType": "SINGLE_CHOICE"
      },
      {
        "questionContent": "市场调查的（），是市场调查方案的核心部分，也是设计调查方案时应该着重考虑的。",
        "questionId": 1465311,
        "answerTime": 0,
        "correct": 2,
        "studentScore": 0,
        "optionList": [
          {
            "optionContent": "目的",
            "optionTitle": "A",
            "sequence": 0,
            "correct": 0
          },
          {
            "optionContent": "项目和工具",
            "optionTitle": "B",
            "sequence": 1,
            "correct": 1
          },
          {
            "optionContent": "调查方法",
            "optionTitle": "C",
            "sequence": 2,
            "correct": 0
          },
          {
            "optionContent": "空间与时间",
            "optionTitle": "D",
            "sequence": 3,
            "correct": 0
          }
        ],
        "studentAnswer": "",
        "canAnswer": 1,
        "analysis": "市场调查的<b>项目和工具</b>，是市场调查方案的核心部分，也是设计调查方案时应该着重考虑的。",
        "avgAnswerTime": 8,
        "avgCorrectRate": "86.0%",
        "score": 1.0,
        "sequence": 19,
        "avgScore": 0.0,
        "questionAnswer": "B",
        "questionSource": "模拟题",
        "mainNodeName": "设计市场调查的项目和工具",
        "analysisType": -1,
        "favorite": 0,
        "questionType": "SINGLE_CHOICE"
      },
      {
        "questionContent": "（）是市场调查从定性认识过渡到定量认识的开始阶段，在市场调查中起着统筹兼顾、统一协调的作用。",
        "questionId": 1630464,
        "answerTime": 0,
        "correct": 2,
        "studentScore": 0,
        "optionList": [
          {
            "optionContent": "市场调查计划制定",
            "optionTitle": "A",
            "sequence": 0,
            "correct": 0
          },
          {
            "optionContent": "市场调查报告制作",
            "optionTitle": "B",
            "sequence": 1,
            "correct": 0
          },
          {
            "optionContent": "市场调查方案设计<br>",
            "optionTitle": "C",
            "sequence": 2,
            "correct": 1
          },
          {
            "optionContent": "市场调查资料收集",
            "optionTitle": "D",
            "sequence": 3,
            "correct": 0
          }
        ],
        "studentAnswer": "",
        "canAnswer": 1,
        "analysis": "<b>​</b>​破题点：开始阶段（方案设计）<br><img src=\"https://sfs-public.shangdejigou.cn/teach-resource/question_content/picture/7db348e0d69f9198cee0a4b8d98fe5f8/image.png\" alt=\"\" width=\"466\" height=\"40\"><br>ABD选项为无关干扰项。故本题正确答案为：C",
        "avgAnswerTime": 31,
        "avgCorrectRate": "85.0%",
        "score": 1.0,
        "sequence": 20,
        "avgScore": 0.0,
        "questionAnswer": "C",
        "questionSource": "模拟题",
        "mainNodeName": "一、市场调查方案设计的含义",
        "analysisType": -1,
        "favorite": 0,
        "questionType": "SINGLE_CHOICE"
      }
    ]
  }
}