{
  "rs": 1,
  "errorCode": "",
  "errorMessage": "",
  "resultMessage": {
    "total": 20,
    "totalSubQuestionNum": 20,
    "questionList": [
      {
        "questionContent": "现代职业具有自身的特性，即区域性、行业性和（ ）",
        "questionId": 2010690,
        "answerTime": 0,
        "correct": 2,
        "studentScore": 0,
        "optionList": [
          {
            "optionContent": "经济性",
            "optionTitle": "A",
            "sequence": 0,
            "correct": 0
          },
          {
            "optionContent": "效益性",
            "optionTitle": "B",
            "sequence": 1,
            "correct": 0
          },
          {
            "optionContent": "岗位性",
            "optionTitle": "C",
            "sequence": 2,
            "correct": 1
          },
          {
            "optionContent": "​<span style=\"font-size: 14px;\">探索性</span><br>",
            "optionTitle": "D",
            "sequence": 3,
            "correct": 0
          }
        ],
        "studentAnswer": "",
        "canAnswer": 1,
        "analysis": "本题破题点：“现代职业”。现代职业具有自身的区域性、行业性、岗位性等特性。<span style=\"font-size: 14px;\">在设计职业生涯规划时，要正确地进行职业分析。故本题的正确答案为C。</span>",
        "avgAnswerTime": 21,
        "avgCorrectRate": "50.0%",
        "score": 1.0,
        "sequence": 1,
        "avgScore": 0.0,
        "errorProneAnswer": "A",
        "questionAnswer": "C",
        "questionSource": "江苏省-1904真题-第1题",
        "mainNodeName": "五、设计职业生涯规划的步骤",
        "analysisType": -1,
        "favorite": 0,
        "questionType": "SINGLE_CHOICE"
      },
      {
        "questionContent": "培训是对成人的（ ）",
        "questionId": 2010665,
        "answerTime": 0,
        "correct": 2,
        "studentScore": 0,
        "optionList": [
          {
            "optionContent": "社会化",
            "optionTitle": "A",
            "sequence": 0,
            "correct": 0
          },
          {
            "optionContent": "再社会化",
            "optionTitle": "B",
            "sequence": 1,
            "correct": 0
          },
          {
            "optionContent": "再灌输",
            "optionTitle": "C",
            "sequence": 2,
            "correct": 0
          },
          {
            "optionContent": "再教育",
            "optionTitle": "D",
            "sequence": 3,
            "correct": 1
          }
        ],
        "studentAnswer": "",
        "canAnswer": 1,
        "analysis": "本题的关键在于理解培训的含义。<span style=\"font-size: 14px;\">员工培训与正规教育不同，它是一种终身的、回归的继续教育，是属于“第二次教育过程”的<b>再教育</b>。故本题的正确答案为D。</span>",
        "avgAnswerTime": 4,
        "avgCorrectRate": "97.0%",
        "score": 1.0,
        "sequence": 2,
        "avgScore": 0.0,
        "questionAnswer": "D",
        "questionSource": "江苏省-1904真题-第1题",
        "mainNodeName": "一、员工培训的含义",
        "analysisType": -1,
        "favorite": 0,
        "questionType": "SINGLE_CHOICE"
      },
      {
        "questionContent": "对于企业不同层次、不同岗位的员工，培训内容、方式有所不同。这说明员工培训应具有（）",
        "questionId": 2298998,
        "answerTime": 0,
        "correct": 2,
        "studentScore": 0,
        "optionList": [
          {
            "optionContent": "广泛性",
            "optionTitle": "A",
            "sequence": 0,
            "correct": 0
          },
          {
            "optionContent": "层次性",
            "optionTitle": "B",
            "sequence": 1,
            "correct": 0
          },
          {
            "optionContent": "针对性",
            "optionTitle": "C",
            "sequence": 2,
            "correct": 1
          },
          {
            "optionContent": "有效性",
            "optionTitle": "D",
            "sequence": 3,
            "correct": 0
          }
        ],
        "studentAnswer": "",
        "canAnswer": 1,
        "analysis": "<b>1.培训具有很强的针对性：针对性是指对于企业不同层次、不同岗位的员工，培训内容、方式有所不同。故本题选C。</b>2.培训的层次性：对不同等级水平的企业人员，由于他们承担的工作任务不同，知识和技术需要各异，因而培训的内容，应当有所不同。3.培训的广泛性：员工培训的网络涉及面广；培训的内容广泛；4.培训的有效性是指培训投资产生的回报。",
        "avgAnswerTime": 7,
        "avgCorrectRate": "90.0%",
        "score": 1.0,
        "sequence": 3,
        "avgScore": 0.0,
        "questionAnswer": "C",
        "questionSource": "江苏省-1307真题-第1题",
        "mainNodeName": "二、员工培训的特点",
        "analysisType": -1,
        "favorite": 0,
        "questionType": "SINGLE_CHOICE"
      },
      {
        "questionContent": "将培训经验经过理论提高而制订的对于培训的基本要求称为（）",
        "questionId": 2404461,
        "answerTime": 0,
        "correct": 2,
        "studentScore": 0,
        "optionList": [
          {
            "optionContent": "培训计划",
            "optionTitle": "A",
            "sequence": 0,
            "correct": 0
          },
          {
            "optionContent": "培训设计",
            "optionTitle": "B",
            "sequence": 1,
            "correct": 0
          },
          {
            "optionContent": "培训原则",
            "optionTitle": "C",
            "sequence": 2,
            "correct": 1
          },
          {
            "optionContent": "培训大纲",
            "optionTitle": "D",
            "sequence": 3,
            "correct": 0
          }
        ],
        "studentAnswer": "",
        "canAnswer": 1,
        "analysis": "本题考核员工培训的原则。培训原则是将培训经验经过理论提高而制订的对于培训的基本要求。故本题选C",
        "avgAnswerTime": 12,
        "avgCorrectRate": "68.0%",
        "score": 1.0,
        "sequence": 4,
        "avgScore": 0.0,
        "errorProneAnswer": "A",
        "questionAnswer": "C",
        "questionSource": "江苏省-1407真题-第1题",
        "mainNodeName": "五、员工培训的原则",
        "analysisType": -1,
        "favorite": 0,
        "questionType": "SINGLE_CHOICE"
      },
      {
        "questionContent": "通过有计划的干预措施来增强组织运作有效性及其成员工作满意度的过程称为（）",
        "questionId": 1575940,
        "answerTime": 0,
        "correct": 2,
        "studentScore": 0,
        "optionList": [
          {
            "optionContent": "组织创新",
            "optionTitle": "A",
            "sequence": 0,
            "correct": 0
          },
          {
            "optionContent": "组织发展",
            "optionTitle": "B",
            "sequence": 1,
            "correct": 1
          },
          {
            "optionContent": "组织建构",
            "optionTitle": "C",
            "sequence": 2,
            "correct": 0
          },
          {
            "optionContent": "组织变革",
            "optionTitle": "D",
            "sequence": 3,
            "correct": 0
          }
        ],
        "studentAnswer": "",
        "canAnswer": 1,
        "analysis": "本题的关键在于理解组织发展的概念，组织发展是通过有计划的干预措施来增强组织运作有效性及其成员工作满意度的过程。故本题的正确答案为B。<br>",
        "avgAnswerTime": 12,
        "avgCorrectRate": "83.0%",
        "score": 1.0,
        "sequence": 5,
        "avgScore": 0.0,
        "questionAnswer": "B",
        "questionSource": "江苏省-1407真题-第1题",
        "mainNodeName": "一、变革过程理论",
        "analysisType": -1,
        "favorite": 0,
        "questionType": "SINGLE_CHOICE"
      },
      {
        "questionContent": "按照经济学的观点，薪酬就是劳动力的价格，取决于劳动力的（ ）",
        "questionId": 2404454,
        "answerTime": 0,
        "correct": 2,
        "studentScore": 0,
        "optionList": [
          {
            "optionContent": "供应总量",
            "optionTitle": "A",
            "sequence": 0,
            "correct": 0
          },
          {
            "optionContent": "供求状况",
            "optionTitle": "B",
            "sequence": 1,
            "correct": 1
          },
          {
            "optionContent": "需求总量",
            "optionTitle": "C",
            "sequence": 2,
            "correct": 0
          },
          {
            "optionContent": "质量状况",
            "optionTitle": "D",
            "sequence": 3,
            "correct": 0
          }
        ],
        "studentAnswer": "",
        "canAnswer": 1,
        "analysis": "破题点：经济学、薪酬按照<b>经济学</b>的观点，薪酬就是劳动力的价格，取决于劳动力的<b>供求状况。B项正确</b>ACD项未提及，为干扰项，排除；故<b>正确答案为B项</b>。",
        "avgAnswerTime": 12,
        "avgCorrectRate": "78.0%",
        "score": 1.0,
        "sequence": 6,
        "avgScore": 0.0,
        "errorProneAnswer": "D",
        "questionAnswer": "B",
        "questionSource": "江苏省-1704真题-第1题",
        "mainNodeName": "企业外部因素",
        "analysisType": -1,
        "favorite": 0,
        "questionType": "SINGLE_CHOICE"
      },
      {
        "questionContent": "第一个对薪酬进行分析的西方学者是（）",
        "questionId": 2404441,
        "answerTime": 0,
        "correct": 2,
        "studentScore": 0,
        "optionList": [
          {
            "optionContent": "威廉•配第",
            "optionTitle": "A",
            "sequence": 0,
            "correct": 0
          },
          {
            "optionContent": "穆勒",
            "optionTitle": "B",
            "sequence": 1,
            "correct": 0
          },
          {
            "optionContent": "亚当•斯密",
            "optionTitle": "C",
            "sequence": 2,
            "correct": 1
          },
          {
            "optionContent": "李嘉图",
            "optionTitle": "D",
            "sequence": 3,
            "correct": 0
          }
        ],
        "studentAnswer": "",
        "canAnswer": 1,
        "analysis": "本题考核早期的薪酬理论。亚当•斯密是第一个对薪酬进行分析的学者，他认为薪酬是在财产所有者与劳动相分离的情况下，作为非财产所有者的劳动者的报酬。故本题选C。<br>",
        "avgAnswerTime": 7,
        "avgCorrectRate": "81.0%",
        "score": 1.0,
        "sequence": 7,
        "avgScore": 0.0,
        "errorProneAnswer": "A",
        "questionAnswer": "C",
        "questionSource": "江苏省-1504真题-第1题",
        "mainNodeName": "早期的薪酬理论",
        "analysisType": -1,
        "favorite": 0,
        "questionType": "SINGLE_CHOICE"
      },
      {
        "questionContent": "由古典经济学的创始人威廉•配第提出的薪酬理论是（）",
        "questionId": 227042,
        "answerTime": 0,
        "correct": 2,
        "studentScore": 0,
        "optionList": [
          {
            "optionContent": "维持生存薪酬理论",
            "optionTitle": "A",
            "sequence": 0,
            "correct": 1
          },
          {
            "optionContent": "边际生产率薪酬理论",
            "optionTitle": "B",
            "sequence": 1,
            "correct": 0
          },
          {
            "optionContent": "人力资本理论",
            "optionTitle": "C",
            "sequence": 2,
            "correct": 0
          },
          {
            "optionContent": "集体谈判薪酬理论",
            "optionTitle": "D",
            "sequence": 3,
            "correct": 0
          }
        ],
        "studentAnswer": "",
        "canAnswer": 1,
        "analysis": "本题考核维持生存薪酬理论。由古典经济学的创始人威廉•配第提出的薪酬理论是维持生存薪酬理论。因此本题选择A。",
        "avgAnswerTime": 12,
        "avgCorrectRate": "80.0%",
        "score": 1.0,
        "sequence": 8,
        "avgScore": 0.0,
        "questionAnswer": "A",
        "questionSource": "江苏省-1304真题-第1题",
        "mainNodeName": "维持生存薪酬理论",
        "analysisType": -1,
        "favorite": 0,
        "questionType": "SINGLE_CHOICE"
      },
      {
        "questionContent": "传统意义上薪酬是一种人力成本的支出，但今天薪酬已成为企业的（）",
        "questionId": 227071,
        "answerTime": 0,
        "correct": 2,
        "studentScore": 0,
        "optionList": [
          {
            "optionContent": "人力资本投资",
            "optionTitle": "A",
            "sequence": 0,
            "correct": 1
          },
          {
            "optionContent": "人力资本教育",
            "optionTitle": "B",
            "sequence": 1,
            "correct": 0
          },
          {
            "optionContent": "人力资本计划",
            "optionTitle": "C",
            "sequence": 2,
            "correct": 0
          },
          {
            "optionContent": "人力资本规划",
            "optionTitle": "D",
            "sequence": 3,
            "correct": 0
          }
        ],
        "studentAnswer": "",
        "canAnswer": 1,
        "analysis": "本题考核人力资本理论。传统意义上薪酬是一种人力成本的支出，但今天薪酬已成为企业的人力资本投资。因此本题选择A。",
        "avgAnswerTime": 16,
        "avgCorrectRate": "81.0%",
        "score": 1.0,
        "sequence": 9,
        "avgScore": 0.0,
        "questionAnswer": "A",
        "questionSource": "江苏省-1307真题-第1题",
        "mainNodeName": "人力资本理论",
        "analysisType": -1,
        "favorite": 0,
        "questionType": "SINGLE_CHOICE"
      },
      {
        "questionContent": "真正提出人力资本理论的经济学家是（ ）",
        "questionId": 2001988,
        "answerTime": 0,
        "correct": 2,
        "viceNodeName1": "边际生产率薪酬理论",
        "studentScore": 0,
        "optionList": [
          {
            "optionContent": "马歇尔",
            "optionTitle": "A",
            "sequence": 0,
            "correct": 0
          },
          {
            "optionContent": "加里·贝克尔",
            "optionTitle": "B",
            "sequence": 1,
            "correct": 0
          },
          {
            "optionContent": "西奥多·舒尔茨",
            "optionTitle": "C",
            "sequence": 2,
            "correct": 1
          },
          {
            "optionContent": "克拉克",
            "optionTitle": "D",
            "sequence": 3,
            "correct": 0
          }
        ],
        "studentAnswer": "",
        "canAnswer": 1,
        "analysis": "破题点：真正提出，人力资本理论<img src=\"https://sfs-public.shangdejigou.cn/teach-resource/question_content/picture/a00bbe425a3fdcdaa2b141d22cbf06f2/image.png\" alt=\"\" width=\"392\" height=\"150\"><br>故本题的<b>正确答案为C项</b>。",
        "avgAnswerTime": 9,
        "avgCorrectRate": "71.0%",
        "score": 1.0,
        "sequence": 10,
        "avgScore": 0.0,
        "errorProneAnswer": "B",
        "questionAnswer": "C",
        "questionSource": "江苏省-1704真题-第1题",
        "viceNodeName2": "供求均衡薪酬论",
        "mainNodeName": "人力资本理论",
        "analysisType": -1,
        "favorite": 0,
        "questionType": "SINGLE_CHOICE"
      },
      {
        "questionContent": "劳动的边际生产率这一概念的提出者是（ ）",
        "questionId": 2404443,
        "answerTime": 0,
        "correct": 2,
        "studentScore": 0,
        "optionList": [
          {
            "optionContent": "克拉克",
            "optionTitle": "A",
            "sequence": 0,
            "correct": 1
          },
          {
            "optionContent": "马歇尔",
            "optionTitle": "B",
            "sequence": 1,
            "correct": 0
          },
          {
            "optionContent": "马克思",
            "optionTitle": "C",
            "sequence": 2,
            "correct": 0
          },
          {
            "optionContent": "加里·贝克尔",
            "optionTitle": "D",
            "sequence": 3,
            "correct": 0
          }
        ],
        "studentAnswer": "",
        "canAnswer": 1,
        "analysis": "破题点：边际生产率<img src=\"https://sfs-public.shangdejigou.cn/teach-resource/question_content/picture/5d2756530027eb4f8fca735728c67b50/image.png\" alt=\"\" width=\"518\" height=\"115\"><br>故<b>本题的正确答案为A项</b>。",
        "avgAnswerTime": 7,
        "avgCorrectRate": "85.0%",
        "score": 1.0,
        "sequence": 11,
        "avgScore": 0.0,
        "errorProneAnswer": "D",
        "questionAnswer": "A",
        "questionSource": "江苏省-1604真题-第1题",
        "mainNodeName": "边际生产率薪酬理论",
        "analysisType": -1,
        "favorite": 0,
        "questionType": "SINGLE_CHOICE"
      },
      {
        "questionContent": "从发达国家的实践来看，福利管理的趋势是社会化和（）",
        "questionId": 228684,
        "answerTime": 0,
        "correct": 2,
        "studentScore": 0,
        "optionList": [
          {
            "optionContent": "货币化",
            "optionTitle": "A",
            "sequence": 0,
            "correct": 1
          },
          {
            "optionContent": "保障性",
            "optionTitle": "B",
            "sequence": 1,
            "correct": 0
          },
          {
            "optionContent": "战略化",
            "optionTitle": "C",
            "sequence": 2,
            "correct": 0
          },
          {
            "optionContent": "计划性",
            "optionTitle": "D",
            "sequence": 3,
            "correct": 0
          }
        ],
        "studentAnswer": "",
        "canAnswer": 1,
        "analysis": "本题考核员工福利管理的社会化和货币化。从发达国家的实践来看，福利管理的趋势是社会化和货币化。故本题选A。",
        "avgAnswerTime": 9,
        "avgCorrectRate": "80.0%",
        "score": 1.0,
        "sequence": 12,
        "avgScore": 0.0,
        "errorProneAnswer": "B",
        "questionAnswer": "A",
        "questionSource": "江苏省-1307真题-第1题",
        "mainNodeName": "员工福利管理的社会化和货币化",
        "analysisType": -1,
        "favorite": 0,
        "questionType": "SINGLE_CHOICE"
      },
      {
        "questionContent": "职业选择是个人能力意向与（ ）",
        "questionId": 2010985,
        "answerTime": 0,
        "correct": 2,
        "studentScore": 0,
        "optionList": [
          {
            "optionContent": "社会岗位的统一",
            "optionTitle": "A",
            "sequence": 0,
            "correct": 1
          },
          {
            "optionContent": "社会需求的统一",
            "optionTitle": "B",
            "sequence": 1,
            "correct": 0
          },
          {
            "optionContent": "职业意向的统一",
            "optionTitle": "C",
            "sequence": 2,
            "correct": 0
          },
          {
            "optionContent": "就业需求的统一",
            "optionTitle": "D",
            "sequence": 3,
            "correct": 0
          }
        ],
        "studentAnswer": "",
        "canAnswer": 1,
        "analysis": "本题破题点：“职业选择”。职业选择是个人对于自己就业方向和工作岗位类别的比较、挑选和确定，是<b>个人能力意向与社会岗位的统一</b>。故本题的正确答案为A。",
        "avgAnswerTime": 8,
        "avgCorrectRate": "63.0%",
        "score": 1.0,
        "sequence": 13,
        "avgScore": 0.0,
        "errorProneAnswer": "C",
        "questionAnswer": "A",
        "questionSource": "江苏省-1904真题-第1题",
        "mainNodeName": "职业选择的含义",
        "analysisType": -1,
        "favorite": 0,
        "questionType": "SINGLE_CHOICE"
      },
      {
        "questionContent": "最早出现的职业选择理论是（）",
        "questionId": 228986,
        "answerTime": 0,
        "correct": 2,
        "studentScore": 0,
        "optionList": [
          {
            "optionContent": "特性与因素理论",
            "optionTitle": "A",
            "sequence": 0,
            "correct": 1
          },
          {
            "optionContent": "职业性向理论",
            "optionTitle": "B",
            "sequence": 1,
            "correct": 0
          },
          {
            "optionContent": "职业锚理论",
            "optionTitle": "C",
            "sequence": 2,
            "correct": 0
          },
          {
            "optionContent": "社会学系理论",
            "optionTitle": "D",
            "sequence": 3,
            "correct": 0
          }
        ],
        "studentAnswer": "",
        "canAnswer": 1,
        "analysis": "本题考核特性与因素理论。特性与因素理论是最早出现的职业选择理论。特性与因素是由帕森斯创立，威廉森发展和成型的。故本题选A。",
        "avgAnswerTime": 11,
        "avgCorrectRate": "66.0%",
        "score": 1.0,
        "sequence": 14,
        "avgScore": 0.0,
        "questionAnswer": "A",
        "questionSource": "江苏省-1404真题-第1题",
        "mainNodeName": "特性与因素理论",
        "analysisType": -1,
        "favorite": 0,
        "questionType": "SINGLE_CHOICE"
      },
      {
        "questionContent": "在霍兰德人格类型中，注重细节讲求精确性，具备记录和归档能力，适合从事办公室工作和一般事务性工作的人的类型属于（）",
        "questionId": 1560574,
        "answerTime": 0,
        "correct": 2,
        "studentScore": 0,
        "optionList": [
          {
            "optionContent": "现实型",
            "optionTitle": "A",
            "sequence": 0,
            "correct": 0
          },
          {
            "optionContent": "常规型",
            "optionTitle": "B",
            "sequence": 1,
            "correct": 1
          },
          {
            "optionContent": "社会型",
            "optionTitle": "C",
            "sequence": 2,
            "correct": 0
          },
          {
            "optionContent": "艺术型",
            "optionTitle": "D",
            "sequence": 3,
            "correct": 0
          }
        ],
        "studentAnswer": "",
        "canAnswer": 1,
        "analysis": "<span style=\"font-size: 14px;\">本题破题点“办公室”、“一般事务性”，而霍兰德的个性类型划分主要如下表所示：</span><img src=\"https://sfs-public.shangdejigou.cn/teach-resource/question_content/picture/70396ab543a53787d0c3f5afa43ec245/1.png\" alt=\"\" width=\"730\" height=\"137\"><span style=\"font-size: 14px;\"><br></span>故本题的正确答案为B。",
        "avgAnswerTime": 7,
        "avgCorrectRate": "91.0%",
        "score": 1.0,
        "sequence": 15,
        "avgScore": 0.0,
        "errorProneAnswer": "A",
        "questionAnswer": "B",
        "questionSource": "江苏省-1804真题-第1题",
        "mainNodeName": "职业性向理论",
        "analysisType": -1,
        "favorite": 0,
        "questionType": "SINGLE_CHOICE"
      },
      {
        "questionContent": "在影响职业生涯的社会因素中，影响人们行为、欲望的基本因素是（）",
        "questionId": 1561168,
        "answerTime": 0,
        "correct": 2,
        "studentScore": 0,
        "optionList": [
          {
            "optionContent": "文化因素",
            "optionTitle": "A",
            "sequence": 0,
            "correct": 1
          },
          {
            "optionContent": "价值观念",
            "optionTitle": "B",
            "sequence": 1,
            "correct": 0
          },
          {
            "optionContent": "经济发展水平",
            "optionTitle": "C",
            "sequence": 2,
            "correct": 0
          },
          {
            "optionContent": "社会阶层",
            "optionTitle": "D",
            "sequence": 3,
            "correct": 0
          }
        ],
        "studentAnswer": "",
        "canAnswer": 1,
        "analysis": "本题破题点：“基本因素”，且需要对这几个社会因素进行区分：<br><img src=\"https://sfs-public.shangdejigou.cn/teach-resource/question_content/picture/796e52c2bd3bc1bb88f96d294830ce03/1.png\" alt=\"\" width=\"754\" height=\"95\"><br>故本题的正确答案为A。",
        "avgAnswerTime": 16,
        "avgCorrectRate": "62.0%",
        "score": 1.0,
        "sequence": 16,
        "avgScore": 0.0,
        "errorProneAnswer": "B",
        "questionAnswer": "A",
        "questionSource": "江苏省-1404真题-第1题",
        "mainNodeName": "社会因素",
        "analysisType": -1,
        "favorite": 0,
        "questionType": "SINGLE_CHOICE"
      },
      {
        "questionContent": "在SWOT分析法中，W代表（ ）",
        "questionId": 2005592,
        "answerTime": 0,
        "correct": 2,
        "studentScore": 0,
        "optionList": [
          {
            "optionContent": "优势",
            "optionTitle": "A",
            "sequence": 0,
            "correct": 0
          },
          {
            "optionContent": "劣势",
            "optionTitle": "B",
            "sequence": 1,
            "correct": 1
          },
          {
            "optionContent": "机会",
            "optionTitle": "C",
            "sequence": 2,
            "correct": 0
          },
          {
            "optionContent": "威胁",
            "optionTitle": "D",
            "sequence": 3,
            "correct": 0
          }
        ],
        "studentAnswer": "",
        "canAnswer": 1,
        "analysis": "<img src=\"https://sfs-public.shangdejigou.cn/teach-resource/question_content/picture/e16d07b626af3a2de38b39ac2f08d744/a.png\" alt=\"\" width=\"304\" height=\"134\"><br>故本题的<b>正确答案为B项</b>。",
        "avgAnswerTime": 3,
        "avgCorrectRate": "97.0%",
        "score": 1.0,
        "sequence": 17,
        "avgScore": 0.0,
        "questionAnswer": "B",
        "questionSource": "江苏省-1604真题-第1题",
        "mainNodeName": "SWOT决策分析法",
        "analysisType": -1,
        "favorite": 0,
        "questionType": "SINGLE_CHOICE"
      },
      {
        "questionContent": "在培训评价的四个层次中，第一个层次是（ ）",
        "questionId": 2001894,
        "answerTime": 0,
        "correct": 2,
        "viceNodeName1": "学习层",
        "studentScore": 0,
        "optionList": [
          {
            "optionContent": "行为层",
            "optionTitle": "A",
            "sequence": 0,
            "correct": 0
          },
          {
            "optionContent": "反应层",
            "optionTitle": "B",
            "sequence": 1,
            "correct": 1
          },
          {
            "optionContent": "​<span style=\"font-size: 14px;\">学习层</span><br>",
            "optionTitle": "C",
            "sequence": 2,
            "correct": 0
          },
          {
            "optionContent": "结果层",
            "optionTitle": "D",
            "sequence": 3,
            "correct": 0
          }
        ],
        "studentAnswer": "",
        "canAnswer": 1,
        "analysis": "破题点：第一个层次<img src=\"https://sfs-public.shangdejigou.cn/teach-resource/question_content/picture/de4b9e72f7250a02fd0d90374848f1ca/image.png\" alt=\"\" width=\"355\" height=\"122\"><br>故本题的<b>正确答案为B项</b>。",
        "avgAnswerTime": 4,
        "avgCorrectRate": "79.0%",
        "score": 1.0,
        "sequence": 18,
        "avgScore": 0.0,
        "errorProneAnswer": "A",
        "questionAnswer": "B",
        "questionSource": "江苏省-1704真题-第1题",
        "viceNodeName2": "行为层",
        "mainNodeName": "反应层",
        "analysisType": -1,
        "favorite": 0,
        "questionType": "SINGLE_CHOICE"
      },
      {
        "questionContent": "美国心理学家赫兹伯格首次在1959年提出的理论是（）",
        "questionId": 1565145,
        "answerTime": 0,
        "correct": 2,
        "studentScore": 0,
        "optionList": [
          {
            "optionContent": "需求层次理论",
            "optionTitle": "A",
            "sequence": 0,
            "correct": 0
          },
          {
            "optionContent": "期望理论",
            "optionTitle": "B",
            "sequence": 1,
            "correct": 0
          },
          {
            "optionContent": "双因素理论",
            "optionTitle": "C",
            "sequence": 2,
            "correct": 1
          },
          {
            "optionContent": "ERG理论",
            "optionTitle": "D",
            "sequence": 3,
            "correct": 0
          }
        ],
        "studentAnswer": "",
        "canAnswer": 1,
        "analysis": "本题破题点：“赫兹伯格”，需要对各个理论及其提出学者进行匹配：<img src=\"https://sfs-public.shangdejigou.cn/teach-resource/question_content/picture/9e45f0132a230626baab6d9132918b90/a.png\" alt=\"\" width=\"295\" height=\"115\"><br>故本题的正确答案为C。",
        "avgAnswerTime": 5,
        "avgCorrectRate": "39.0%",
        "score": 1.0,
        "sequence": 19,
        "avgScore": 0.0,
        "errorProneAnswer": "",
        "questionAnswer": "C",
        "questionSource": "江苏省-1804真题-第30题",
        "mainNodeName": "赫茨伯格双因素理论",
        "analysisType": -1,
        "favorite": 0,
        "questionType": "SINGLE_CHOICE"
      },
      {
        "questionContent": "属于激励的非物质手段的是（）",
        "questionId": 1567262,
        "answerTime": 0,
        "correct": 2,
        "studentScore": 0,
        "optionList": [
          {
            "optionContent": "参与决策，共同设置目标",
            "optionTitle": "A",
            "sequence": 0,
            "correct": 1
          },
          {
            "optionContent": "带薪休假、员工餐厅",
            "optionTitle": "B",
            "sequence": 1,
            "correct": 0
          },
          {
            "optionContent": "技能培训、职务晋升",
            "optionTitle": "C",
            "sequence": 2,
            "correct": 0
          },
          {
            "optionContent": "员工持股和股票期权满足",
            "optionTitle": "D",
            "sequence": 3,
            "correct": 0
          }
        ],
        "studentAnswer": "",
        "canAnswer": 1,
        "analysis": "本题破题点：“非物质手段”，关键在于区分激励的物质手段和非物质手段，如下表所示：<img src=\"https://sfs-public.shangdejigou.cn/teach-resource/question_content/picture/440f0c59e4a5524567849c4c5b6f4d66/a.png\" alt=\"\" width=\"776\" height=\"51\"><br>故本题的正确答案为A。",
        "avgAnswerTime": 10,
        "avgCorrectRate": "88.0%",
        "score": 1.0,
        "sequence": 20,
        "avgScore": 0.0,
        "errorProneAnswer": "C",
        "questionAnswer": "A",
        "questionSource": "江苏省-1504真题-第1题",
        "mainNodeName": "非物质手段",
        "analysisType": -1,
        "favorite": 0,
        "questionType": "SINGLE_CHOICE"
      }
    ]
  }
}